CHANGES.txt
MANIFEST.in
README.rst
TESTS.rst
setup.py
src/lovely/__init__.py
src/lovely.testlayers.egg-info/PKG-INFO
src/lovely.testlayers.egg-info/SOURCES.txt
src/lovely.testlayers.egg-info/dependency_links.txt
src/lovely.testlayers.egg-info/namespace_packages.txt
src/lovely.testlayers.egg-info/not-zip-safe
src/lovely.testlayers.egg-info/requires.txt
src/lovely.testlayers.egg-info/top_level.txt
src/lovely/testlayers/__init__.py
src/lovely/testlayers/apacheds.py
src/lovely/testlayers/apacheds.txt
src/lovely/testlayers/cass.py
src/lovely/testlayers/cass.txt
src/lovely/testlayers/layer.py
src/lovely/testlayers/layer.txt
src/lovely/testlayers/mail.py
src/lovely/testlayers/mail.txt
src/lovely/testlayers/memcached.py
src/lovely/testlayers/memcached.txt
src/lovely/testlayers/mongodb.py
src/lovely/testlayers/mongodb_masterslave.txt
src/lovely/testlayers/mongodb_replicaset.txt
src/lovely/testlayers/mongodb_single.txt
src/lovely/testlayers/mysql.py
src/lovely/testlayers/mysql.txt
src/lovely/testlayers/nginx.py
src/lovely/testlayers/nginx.txt
src/lovely/testlayers/openldap.py
src/lovely/testlayers/openldap.txt
src/lovely/testlayers/pgsql.py
src/lovely/testlayers/pgsql.txt
src/lovely/testlayers/postgresql8.2.conf
src/lovely/testlayers/postgresql8.3.conf
src/lovely/testlayers/postgresql8.4.conf
src/lovely/testlayers/server.py
src/lovely/testlayers/server.txt
src/lovely/testlayers/sql.py
src/lovely/testlayers/tests.py
src/lovely/testlayers/util.py