Metadata-Version: 1.0
Name: lovely.testlayers
Version: 0.7.1
Summary: test layers for use with zope.testrunner: apacheds, cassandra, memcached, mongodb, mysql, nginx, openldap, postgresql
Home-page: https://github.com/lovelysystems/lovely.testlayers
Author: Lovely Systems
Author-email: office@lovelysystems.com
License: Apache License 2.0
Keywords: testing zope layer test apacheds cassandra memcached mongodb mysql nginx openldap postgresql
Platform: UNKNOWN
